{
  "code": 0,
  "msg": "ok",
  "data": [
    {
      "rzbh": 30070,
	  "xtmk": "代码生成",
      "czlx": "导入",
      "czry": "admin",
      "bmmc": "研发部门",
	  "zj": "124.6.155.2",
	  "czdd":"安蒂克省 XX",
	  "czzt":"成功",
	  "czsj":"2019-07-24 11:30:31"
    },
	{
	  "rzbh": 30069,
	  "xtmk": "角色管理",
	  "czlx": "授权",
	  "czry": "admin",
	  "bmmc": "研发部门",
	  "zj": "183.14.30.3",
	  "czdd":"广东 深圳",
	  "czzt":"成功",
	  "czsj":"2019-07-24 11:30:31"
	},
	{
	  "rzbh": 30069,
	  "xtmk": "角色管理",
	  "czlx": "授权",
	  "czry": "admin",
	  "bmmc": "研发部门",
	  "zj": "183.14.30.3",
	  "czdd":"广东 深圳",
	  "czzt":"成功",
	  "czsj":"2019-07-24 11:30:31"
	},
	{
	  "rzbh": 30069,
	  "xtmk": "角色管理",
	  "czlx": "授权",
	  "czry": "admin",
	  "bmmc": "研发部门",
	  "zj": "183.14.30.3",
	  "czdd":"广东 深圳",
	  "czzt":"成功",
	  "czsj":"2019-07-24 11:30:31"
	},
	{
	  "rzbh": 30069,
	  "xtmk": "角色管理",
	  "czlx": "授权",
	  "czry": "admin",
	  "bmmc": "研发部门",
	  "zj": "183.14.30.3",
	  "czdd":"广东 深圳",
	  "czzt":"成功",
	  "czsj":"2019-07-24 11:30:31"
	},
	{
	  "rzbh": 30069,
	  "xtmk": "角色管理",
	  "czlx": "授权",
	  "czry": "admin",
	  "bmmc": "研发部门",
	  "zj": "183.14.30.3",
	  "czdd":"广东 深圳",
	  "czzt":"成功",
	  "czsj":"2019-07-24 11:30:31"
	}
  ],
  "count": 4
  }